{
  "Cell Dev Completer": [
    "Complete CDC Modules M1–M4",
    "Meet mentor 4×",
    "Serve consistently for 8 weeks"
  ],
  "BS Leader": [
    "Prepare 3 outlines",
    "Lead 6 sessions",
    "Weekly report 8/10 weeks"
  ],
  "HF Leader": [
    "Host 4 HFs",
    "Rotate facilitators",
    "Integrate prayer & care loop"
  ],
  "DCL": [
    "Coach 2 BS leaders",
    "Multiply 1 group",
    "Monthly leader huddle"
  ],
  "Outreach Leader": [
    "Draft outreach VMV",
    "Establish pipeline cadence",
    "Community engagement plan"
  ]
}